modalogic/__init__.py
modalogic/cli.py
modalogic/modalogic.py
modalogic-0.0.1.dist-info/LICENSE
modalogic-0.0.1.dist-info/METADATA
modalogic-0.0.1.dist-info/WHEEL
modalogic-0.0.1.dist-info/entry_points.txt
modalogic-0.0.1.dist-info/top_level.txt
modalogic-0.0.1.dist-info/RECORD
