Metadata-Version: 2.1
Name: modalogic
Version: 0.0.1
Summary: A research package modal-logic based reasoning using the Analytical Tableaux method.
Home-page: https://github.com/rayniervanegmond/modalogic
Author: Raynier van Egmond
Author-email: raynierx@gmail.com
License: GNU General Public License v3
Keywords: modalogic
Platform: UNKNOWN
Classifier: Development Status :: 2 - Pre-Alpha
Classifier: Intended Audience :: Developers
Classifier: License :: OSI Approved :: GNU General Public License v3 (GPLv3)
Classifier: Natural Language :: English
Classifier: Programming Language :: Python :: 3
Classifier: Programming Language :: Python :: 3.5
Classifier: Programming Language :: Python :: 3.6
Classifier: Programming Language :: Python :: 3.7
Classifier: Programming Language :: Python :: 3.8
Requires-Python: >=3.5
